{
  "trigger": {
    "disableBlock": false,
    "description": "",
    "type": "",
    "interval": 0,
    "delay": 0,
    "date": "",
    "time": "",
    "url": "",
    "shortcut": "",
    "activeInInput": false,
    "isUrlRegex": false,
    "days": [],
    "contextMenuName": "",
    "contextTypes": [],
    "parameters": [],
    "preferParamsInTab": false,
    "observeElement": {}
  },
  "ai-workflow": {
    "disableBlock": false,
    "flowUuid": "",
    "flowLabel": "",
    "description": "",
    "inputs": [],
    "outputs": [],
    "assignVariable": false,
    "variableName": "",
    "saveData": false,
    "dataColumn": ""
  },
  "execute-workflow": {
    "disableBlock": false,
    "executeId": "",
    "workflowId": "",
    "globalData": "",
    "description": "",
    "insertAllVars": false,
    "insertAllGlobalData": false
  },
  "active-tab": {
    "disableBlock": false
  },
  "new-tab": {
    "disableBlock": false,
    "description": "",
    "url": "",
    "userAgent": "",
    "active": false,
    "tabZoom": 0,
    "inGroup": false,
    "waitTabLoaded": false,
    "updatePrevTab": false,
    "customUserAgent": false
  },
  "switch-tab": {
    "disableBlock": false,
    "description": "",
    "url": "",
    "tabIndex": 0,
    "tabTitle": "",
    "matchPattern": "",
    "activeTab": false,
    "createIfNoMatch": false,
    "findTabBy": ""
  },
  "new-window": {
    "disableBlock": false,
    "description": "",
    "top": 0,
    "left": 0,
    "width": 0,
    "url": "",
    "height": 0,
    "type": "",
    "incognito": false,
    "windowState": ""
  },
  "proxy": {
    "description": "",
    "disableBlock": false,
    "scheme": "",
    "host": "",
    "port": 0,
    "bypassList": "",
    "clearProxy": false
  },
  "go-back": {
    "disableBlock": false
  },
  "forward-page": {
    "disableBlock": false
  },
  "close-tab": {
    "disableBlock": false,
    "url": "",
    "description": "",
    "activeTab": false,
    "closeType": "",
    "allWindows": false
  },
  "take-screenshot": {
    "description": "",
    "disableBlock": false,
    "fileName": "",
    "ext": "",
    "quality": 0,
    "dataColumn": "",
    "variableName": "",
    "selector": "",
    "fullPage": false,
    "saveToColumn": false,
    "saveToComputer": false,
    "assignVariable": false,
    "captureActiveTab": false
  },
  "browser-event": {
    "disableBlock": false,
    "description": "",
    "timeout": 0,
    "eventName": "",
    "setAsActiveTab": false,
    "activeTabLoaded": false,
    "tabLoadedUrl": "",
    "tabUrl": "",
    "fileQuery": ""
  },
  "event-click": {
    "disableBlock": false,
    "description": "",
    "findBy": "",
    "waitForSelector": false,
    "waitSelectorTimeout": 0,
    "selector": "",
    "markEl": false,
    "multiple": false
  },
  "delay": {
    "disableBlock": false,
    "time": 0
  },
  "get-text": {
    "disableBlock": false,
    "description": "",
    "findBy": "",
    "waitForSelector": false,
    "waitSelectorTimeout": 0,
    "selector": "",
    "markEl": false,
    "multiple": false,
    "regex": "",
    "prefixText": "",
    "suffixText": "",
    "regexExp": [],
    "dataColumn": "",
    "saveData": false,
    "includeTags": false,
    "addExtraRow": false,
    "assignVariable": false,
    "useTextContent": false,
    "variableName": "",
    "extraRowValue": "",
    "extraRowDataColumn": ""
  },
  "export-data": {
    "disableBlock": false,
    "name": "",
    "refKey": "",
    "type": "",
    "description": "",
    "variableName": "",
    "csvDelimiter": "",
    "addBOMHeader": false,
    "onConflict": "",
    "dataToExport": ""
  },
  "element-scroll": {
    "disableBlock": false,
    "description": "",
    "findBy": "",
    "waitForSelector": false,
    "waitSelectorTimeout": 0,
    "selector": "",
    "markEl": false,
    "multiple": false,
    "scrollY": 0,
    "scrollX": 0,
    "incX": false,
    "incY": false,
    "smooth": false,
    "scrollIntoView": false
  },
  "link": {
    "disableBlock": false,
    "description": "",
    "findBy": "",
    "waitForSelector": false,
    "waitSelectorTimeout": 0,
    "selector": "",
    "markEl": false,
    "disableMultiple": false,
    "openInNewTab": false
  },
  "attribute-value": {
    "disableBlock": false,
    "description": "",
    "findBy": "",
    "waitForSelector": false,
    "waitSelectorTimeout": 0,
    "selector": "",
    "markEl": false,
    "multiple": false,
    "attributeValue": "",
    "attributeName": "",
    "assignVariable": false,
    "variableName": "",
    "dataColumn": "",
    "saveData": false,
    "action": "",
    "addExtraRow": false,
    "extraRowValue": "",
    "extraRowDataColumn": ""
  },
  "forms": {
    "disableBlock": false,
    "description": "",
    "findBy": "",
    "waitForSelector": false,
    "waitSelectorTimeout": 0,
    "selector": "",
    "markEl": false,
    "multiple": false,
    "selected": false,
    "clearValue": false,
    "getValue": false,
    "saveData": false,
    "dataColumn": "",
    "selectOptionBy": "",
    "optionPosition": "",
    "assignVariable": false,
    "variableName": "",
    "type": "",
    "value": "",
    "delay": 0,
    "events": []
  },
  "repeat-task": {
    "disableBlock": false,
    "repeatFor": ""
  },
  "javascript-code": {
    "disableBlock": false,
    "description": "",
    "timeout": 0,
    "context": "",
    "code": "",
    "preloadScripts": [],
    "everyNewTab": false,
    "runBeforeLoad": false
  },
  "trigger-event": {
    "disableBlock": false,
    "description": "",
    "findBy": "",
    "waitForSelector": false,
    "waitSelectorTimeout": 0,
    "selector": "",
    "markEl": false,
    "multiple": false,
    "eventName": "",
    "eventType": "",
    "eventParams": {}
  },
  "google-sheets": {
    "disableBlock": false,
    "range": "",
    "refKey": "",
    "type": "",
    "customData": "",
    "description": "",
    "spreadsheetId": "",
    "dataColumn": "",
    "saveData": false,
    "assignVariable": false,
    "variableName": "",
    "firstRowAsKey": false,
    "keysAsFirstRow": false,
    "valueInputOption": "",
    "InsertDataOption": "",
    "dataFrom": ""
  },
  "google-sheets-drive": {
    "disableBlock": false,
    "range": "",
    "refKey": "",
    "type": "",
    "customData": "",
    "description": "",
    "spreadsheetId": "",
    "dataColumn": "",
    "inputSpreadsheetId": "",
    "saveData": false,
    "sheetName": "",
    "assignVariable": false,
    "variableName": "",
    "firstRowAsKey": false,
    "keysAsFirstRow": false,
    "valueInputOption": "",
    "InsertDataOption": "",
    "dataFrom": ""
  },
  "google-drive": {
    "disableBlock": false,
    "action": "",
    "filePaths": []
  },
  "conditions": {
    "description": "",
    "disableBlock": false,
    "conditions": [],
    "retryConditions": false,
    "retryCount": 0,
    "retryTimeout": 0
  },
  "element-exists": {
    "disableBlock": false,
    "description": "",
    "findBy": "",
    "selector": "",
    "tryCount": 0,
    "timeout": 0,
    "markEl": false,
    "throwError": false
  },
  "webhook": {
    "disableBlock": false,
    "description": "",
    "url": "",
    "body": "",
    "headers": [],
    "method": "",
    "timeout": 0,
    "dataPath": "",
    "contentType": "",
    "variableName": "",
    "assignVariable": false,
    "saveData": false,
    "dataColumn": "",
    "responseType": ""
  },
  "while-loop": {
    "disableBlock": false,
    "description": "",
    "conditions": ""
  },
  "loop-data": {
    "disableBlock": false,
    "loopId": "",
    "maxLoop": 0,
    "toNumber": 0,
    "fromNumber": 0,
    "startIndex": 0,
    "loopData": "",
    "description": "",
    "variableName": "",
    "referenceKey": "",
    "reverseLoop": false,
    "elementSelector": "",
    "waitForSelector": false,
    "waitSelectorTimeout": 0,
    "resumeLastWorkflow": false,
    "loopThrough": ""
  },
  "loop-elements": {
    "disableBlock": false,
    "loopId": "",
    "selector": "",
    "maxLoop": "",
    "description": "",
    "reverseLoop": false,
    "actionElSelector": "",
    "findBy": "",
    "actionElMaxWaitTime": 0,
    "actionPageMaxWaitTime": 0,
    "loadMoreAction": "",
    "scrollToBottom": false,
    "waitForSelector": false,
    "waitSelectorTimeout": 0
  },
  "loop-breakpoint": {
    "disableBlock": false,
    "loopId": "",
    "clearLoop": false
  },
  "blocks-group": {
    "disableBlock": false,
    "name": "",
    "blocks": []
  },
  "clipboard": {
    "disableBlock": false,
    "description": "",
    "type": "",
    "assignVariable": false,
    "variableName": "",
    "saveData": false,
    "dataColumn": "",
    "dataToCopy": "",
    "copySelectedText": false
  },
  "insert-data": {
    "disableBlock": false,
    "description": "",
    "dataList": []
  },
  "switch-to": {
    "disableBlock": false,
    "findBy": "",
    "selector": "",
    "windowType": ""
  },
  "upload-file": {
    "disableBlock": false,
    "findBy": "",
    "waitForSelector": false,
    "waitSelectorTimeout": 0,
    "selector": "",
    "filePaths": []
  },
  "hover-element": {
    "disableBlock": false,
    "description": "",
    "findBy": "",
    "waitForSelector": false,
    "waitSelectorTimeout": 0,
    "selector": "",
    "markEl": false,
    "multiple": false
  },
  "save-assets": {
    "disableBlock": false,
    "description": "",
    "findBy": "",
    "waitForSelector": false,
    "waitSelectorTimeout": 0,
    "selector": "",
    "markEl": false,
    "multiple": false,
    "type": "",
    "url": "",
    "filename": "",
    "saveDownloadIds": false,
    "onConflict": "",
    "dataColumn": "",
    "saveData": false,
    "assignVariable": false,
    "variableName": "",
    "saveToGDrive": false
  },
  "press-key": {
    "disableBlock": false,
    "keys": "",
    "selector": "",
    "pressTime": "",
    "description": "",
    "keysToPress": "",
    "action": ""
  },
  "handle-dialog": {
    "disableBlock": false,
    "description": "",
    "accept": false,
    "promptText": ""
  },
  "handle-download": {
    "disableBlock": false,
    "description": "",
    "filename": "",
    "timeout": 0,
    "onConflict": "",
    "waitForDownload": false,
    "dataColumn": "",
    "saveData": false,
    "assignVariable": false,
    "variableName": "",
    "downloadId": ""
  },
  "reload-tab": {
    "disableBlock": false
  },
  "delete-data": {
    "disableBlock": false,
    "description": "",
    "deleteList": []
  },
  "wait-connections": {
    "disableBlock": false,
    "description": "",
    "timeout": 0,
    "specificFlow": false,
    "flowBlockId": ""
  },
  "notification": {
    "disableBlock": false,
    "description": "",
    "message": "",
    "iconUrl": "",
    "imageUrl": "",
    "title": ""
  },
  "log-data": {
    "disableBlock": false,
    "description": "",
    "workflowId": "",
    "dataColumn": "",
    "saveData": false,
    "assignVariable": false,
    "variableName": ""
  },
  "tab-url": {
    "disableBlock": false,
    "description": "",
    "type": "",
    "dataColumn": "",
    "saveData": false,
    "assignVariable": false,
    "variableName": "",
    "qTitle": "",
    "qMatchPatterns": ""
  },
  "slice-variable": {
    "disableBlock": false,
    "description": "",
    "endIdxEnabled": false,
    "startIdxEnabled": false,
    "endIndex": 0,
    "startIndex": 0,
    "variableName": ""
  },
  "increase-variable": {
    "disableBlock": false,
    "description": "",
    "increaseBy": 0,
    "variableName": ""
  },
  "regex-variable": {
    "disableBlock": false,
    "method": "",
    "replaceVal": "",
    "description": "",
    "expression": "",
    "flag": []
  },
  "data-mapping": {
    "disableBlock": false,
    "description": "",
    "dataSource": "",
    "sources": [],
    "varSourceName": "",
    "dataColumn": "",
    "saveData": false,
    "assignVariable": false,
    "variableName": ""
  },
  "sort-data": {
    "disableBlock": false,
    "description": "",
    "sortByProperty": false,
    "itemProperties": [],
    "dataSource": "",
    "varSourceName": "",
    "dataColumn": "",
    "saveData": false,
    "assignVariable": false,
    "variableName": ""
  },
  "create-element": {
    "disableBlock": false,
    "description": "",
    "javascript": "",
    "html": "",
    "css": "",
    "preloadScripts": [],
    "findBy": "",
    "insertAt": "",
    "runBeforeLoad": false,
    "waitForSelector": false,
    "waitSelectorTimeout": 0,
    "selector": ""
  },
  "cookie": {
    "disableBlock": false,
    "description": "",
    "type": "",
    "jsonCode": "",
    "useJson": false,
    "getAll": false,
    "domain": "",
    "expirationDate": "",
    "path": "",
    "sameSite": "",
    "name": "",
    "url": "",
    "value": "",
    "httpOnly": false,
    "secure": false,
    "session": false,
    "assignVariable": false,
    "variableName": "",
    "saveData": false,
    "dataColumn": ""
  },
  "block-package": {},
  "note": {
    "disableBlock": false,
    "note": "",
    "drawing": false,
    "width": 0,
    "height": 0,
    "color": "",
    "fontSize": ""
  },
  "workflow-state": {
    "disableBlock": false,
    "description": "",
    "type": "",
    "exceptCurrent": false,
    "workflowsToStop": [],
    "throwError": false,
    "errorMessage": ""
  },
  "parameter-prompt": {
    "disableBlock": false,
    "description": "",
    "timeout": 0,
    "parameters": []
  }
}